{
  "biome_distribution_of_land": {
    "beach": 0.051486,
    "desert": 0.094645,
    "forest": 0.052326,
    "mountain": 0.236116,
    "plains": 0.367581,
    "tundra": 0.197846
  },
  "continent_center_count": 4,
  "height": 256,
  "land_component_count": 5,
  "land_fraction": 0.099876,
  "land_tiles": 13091,
  "landmass_sizes": [
    4132,
    3093,
    3069,
    2748
  ],
  "largest_landmass_fraction": 0.315637,
  "largest_landmass_tiles": 4132,
  "ocean_fraction": 0.900124,
  "ocean_tiles": 117981,
  "seed": 42,
  "significant_landmass_count": 4,
  "significant_landmass_min_size": 200,
  "total_tiles": 131072,
  "width": 512
}
